aio_live_task_traces/__init__.py
aio_live_task_traces/live_task_traces_factory.py
tests/test_setting_traces_off.py
tests/test_setting_traces_on.py
aio_live_task_traces-0.0.2.dist-info/LICENSE
aio_live_task_traces-0.0.2.dist-info/METADATA
aio_live_task_traces-0.0.2.dist-info/WHEEL
aio_live_task_traces-0.0.2.dist-info/top_level.txt
aio_live_task_traces-0.0.2.dist-info/RECORD
