Metadata-Version: 2.1
Name: aio-live-task-traces
Version: 0.0.2
Summary: Trace python asyncio tasks exceptions live
Author: Matan Perelman
Author-email: matan1008@gmail.com
License: GNU GENERAL PUBLIC LICENSE
Project-URL: Homepage, https://github.com/matan1008/aio-live-task-traces
Project-URL: Source, https://github.com/matan1008/aio-live-task-traces
Classifier: Programming Language :: Python :: 3.8
Classifier: Programming Language :: Python :: 3.8
Classifier: Programming Language :: Python :: 3.9
Classifier: Programming Language :: Python :: 3.10
Classifier: Programming Language :: Python :: 3.11
Requires-Python: >=3.8
License-File: LICENSE
Provides-Extra: testing
Requires-Dist: pytest ; extra == 'testing'
